CHANGELOG.rst
DESCRIPTION.rst
MANIFEST.in
README.rst
setup.py
hcplogs/__init__.py
hcplogs/__main__.py
hcplogs/init.py
hcplogs/loghandler.py
hcplogs/template.py
hcplogs.egg-info/PKG-INFO
hcplogs.egg-info/SOURCES.txt
hcplogs.egg-info/dependency_links.txt
hcplogs.egg-info/entry_points.txt
hcplogs.egg-info/requires.txt
hcplogs.egg-info/top_level.txt