Metadata-Version: 1.1
Name: hcplogs
Version: 2.0.9
Summary: HCP access log collection utility
Home-page: https://gitlab.com/simont3/hcplogs
Author: Thorsten Simons
Author-email: sw@snomis.de
License: MIT
Keywords: HCP access log Hitachi Content Platform
Platform: UNKNOWN
Classifier: Development Status :: 5 - Production/Stable
Classifier: Intended Audience :: System Administrators
Classifier: Topic :: System :: Archiving
Classifier: Topic :: System :: Logging
Classifier: License :: OSI Approved :: MIT License
Classifier: Programming Language :: Python :: 3.4
Classifier: Operating System :: OS Independent
Classifier: Natural Language :: English
